colors/__init__.py
colors_boss_space-0.0.3.dist-info/LICENSE
colors_boss_space-0.0.3.dist-info/METADATA
colors_boss_space-0.0.3.dist-info/WHEEL
colors_boss_space-0.0.3.dist-info/top_level.txt
colors_boss_space-0.0.3.dist-info/RECORD
