Metadata-Version: 2.1
Name: colors-boss-space
Version: 0.0.3
Summary: colors!
Home-page: https://github.com/boss-space/colors
Author: boss_space
Author-email: buhoizeon@gmail.com
License: UNKNOWN
Platform: UNKNOWN
Classifier: Programming Language :: Python :: 3
Classifier: License :: OSI Approved :: MIT License
Classifier: Operating System :: MacOS
Requires-Python: >=3.8
